messes-1.0.1.data/platlib/_custom_build.py
messes-1.0.1.data/platlib/messes/.gitignore
messes-1.0.1.data/platlib/messes/__init__.py
messes-1.0.1.data/platlib/messes/__main__.py
messes-1.0.1.data/platlib/messes/_version.py
messes-1.0.1.data/platlib/messes/convert/__init__.py
messes-1.0.1.data/platlib/messes/convert/convert.py
messes-1.0.1.data/platlib/messes/convert/convert_schema.py
messes-1.0.1.data/platlib/messes/convert/mwtab_conversion_directives.py
messes-1.0.1.data/platlib/messes/convert/mwtab_functions.py
messes-1.0.1.data/platlib/messes/convert/user_input_checking.py
messes-1.0.1.data/platlib/messes/extract/__init__.py
messes-1.0.1.data/platlib/messes/extract/cythonized_tagSheet.cp310-win_amd64.pyd
messes-1.0.1.data/platlib/messes/extract/cythonized_tagSheet.pyx
messes-1.0.1.data/platlib/messes/extract/extract.py
messes-1.0.1.data/platlib/messes/extract/tagSheet.py
messes-1.0.1.data/platlib/messes/validate/__init__.py
messes-1.0.1.data/platlib/messes/validate/validate.py
messes-1.0.1.data/platlib/messes/validate/validate_schema.py
messes-1.0.1.dist-info/LICENSE
messes-1.0.1.dist-info/METADATA
messes-1.0.1.dist-info/WHEEL
messes-1.0.1.dist-info/entry_points.txt
messes-1.0.1.dist-info/top_level.txt
messes-1.0.1.dist-info/RECORD
