Metadata-Version: 2.1
Name: messes
Version: 1.0.1
Summary: Extract, validate, and convert tabular data for deposition into repositories.
License: The Clear BSD License
Project-URL: Homepage, https://github.com/MoseleyBioinformaticsLab/MESSES
Project-URL: Documentation, https://moseleybioinformaticslab.github.io/MESSES/
Project-URL: GitHub, https://github.com/MoseleyBioinformaticsLab/MESSES
Project-URL: Issues, https://github.com/MoseleyBioinformaticsLab/MESSES/issues
Keywords: mwtab,metabolomics workbench
Classifier: Environment :: Console
Classifier: Intended Audience :: Developers
Classifier: Intended Audience :: Science/Research
Classifier: License :: OSI Approved :: BSD License
Classifier: Operating System :: OS Independent
Classifier: Programming Language :: Python :: 3.10
Classifier: Topic :: Scientific/Engineering :: Bio-Informatics
Classifier: Topic :: Software Development :: Libraries :: Python Modules
Requires-Python: >=3.10
License-File: LICENSE
Requires-Dist: docopt (>=0.6.2)
Requires-Dist: jsonschema (>=4.4.0)
Requires-Dist: pandas (>=0.24.2)
Requires-Dist: openpyxl (>=2.6.2)
Requires-Dist: jellyfish (>=0.9.0)
Requires-Dist: mwtab (>=1.2.5)
Requires-Dist: numpy (>=1.22.4)
Requires-Dist: xlsxwriter (>=3.0.3)
